Metadata-Version: 2.1
Name: PythonLogging
Version: 1.0.0
Summary: A simple logging library for easy log file management
Home-page: https://github.com/SForces/PythonLogging
Author: Osman TUNA
Classifier: Programming Language :: Python :: 3
Classifier: License :: OSI Approved :: MIT License
Classifier: Operating System :: OS Independent
Requires-Python: >=3.6
